[
  {
    "surah": 1,
    "ayah": 1,
    "text_am": "በስማ ሪበሊ ሪሒመተ ሪርሮሖ"
  },
  {
    "surah": 1,
    "ayah": 2,
    "text_am": "ሀመደውልሊ ሪበደ ሊለመተ ሪለግመተ"
  },
  {
    "surah": 1,
    "ayah": 3,
    "text_am": "መሊክ ዮመ ልደ"
  },
  {
    "surah": 1,
    "ayah": 4,
    "text_am": "ኢየሒ ወ ናሕነ ነስታዖገ"
  },
  {
    "surah": 1,
    "ayah": 5,
    "text_am": "ኢየሐይየ ፍሳግ ሊደገ"
  },
  {
    "surah": 1,
    "ayah": 6,
    "text_am": "ሢረጥ ሪጡ ምደግርሦ"
  },
  {
    "surah": 1,
    "ayah": 7,
    "text_am": "ኦ ሊደገ ወ ሊ ሪደልመተ"
  },
  {
    "surah": 2,
    "ayah": 1,
    "text_am": "አሊም"
  },
  {
    "surah": 2,
    "ayah": 2,
    "text_am": "ዐሊከ ሊ ሪበ ውልሊ ሩተ"
  },
  {
    "surah": 2,
    "ayah": 3,
    "text_am": "ሪመነ ኢዩሲ ሩቅ ወ ሪም ሪሰላት"
  },
  {
    "surah": 112,
    "ayah": 1,
    "text_am": "ውል ሑወ አላህ አሕድ"
  },
  {
    "surah": 112,
    "ayah": 2,
    "text_am": "አላህ ሙሳመድ"
  },
  {
    "surah": 112,
    "ayah": 3,
    "text_am": "ለም ዬሊድ ወ ለም ወላድ"
  },
  {
    "surah": 112,
    "ayah": 4,
    "text_am": "ወ ለም ያክን ለሑ ክፋውን አሕድ"
  }
]
